optional_dependency_manager/__init__.py
optional_dependency_manager/odm.py
optional_dependency_manager/py.typed
optional_dependency_manager-0.2.0.dist-info/WHEEL
optional_dependency_manager-0.2.0.dist-info/METADATA
optional_dependency_manager-0.2.0.dist-info/RECORD
