Metadata-Version: 2.3
Name: optional-dependency-manager
Version: 0.2.0
Summary: A Python optional dependency manager.
Keywords: dependency
Author: Fangchen Li
Author-email: Fangchen Li <fangchen.li@outlook.com>
License: MIT License
Classifier: Development Status :: 4 - Beta
Classifier: Intended Audience :: Developers
Classifier: Operating System :: OS Independent
Classifier: License :: OSI Approved :: MIT License
Classifier: Programming Language :: Python :: 3
Classifier: Programming Language :: Python :: 3.10
Classifier: Programming Language :: Python :: 3.11
Classifier: Programming Language :: Python :: 3.12
Classifier: Programming Language :: Python :: 3.13
Classifier: Programming Language :: Python :: 3.14
Classifier: Typing :: Typed
Requires-Dist: packaging
Requires-Dist: tomli>=2.0 ; python_full_version < '3.11'
Requires-Dist: dependency-groups>=1.0 ; extra == 'groups'
Requires-Python: >=3.10
Provides-Extra: groups
